rmrk_tools/__init__.py
rmrk_tools/rmrk1_0_0/__init__.py
rmrk_tools/rmrk2_0_0/__init__.py
py_rmrk_tools-0.1.0a13.dist-info/METADATA
py_rmrk_tools-0.1.0a13.dist-info/WHEEL
py_rmrk_tools-0.1.0a13.dist-info/licenses/LICENSE
py_rmrk_tools-0.1.0a13.dist-info/RECORD
