Metadata-Version: 2.1
Name: py-rmrk-tools
Version: 0.1.0a13
Summary: Python port of Typescript rmrk-tools.
Project-URL: Homepage, https://github.com/khssnv/py-rmrk-tools
Author-email: "Alisher A. Khassanov" <a.khssnv@gmail.com>
License-File: LICENSE
Keywords: kusama,nft,polkadot,rmrk
Requires-Python: >=3.9
Provides-Extra: all
Requires-Dist: black<22.0,>=21.12b0; extra == 'all'
Requires-Dist: flake8<5.0.0,>=4.0.1; extra == 'all'
Requires-Dist: ipython<8.0.0,>=7.30.1; extra == 'all'
Requires-Dist: isort<6.0.0,>=5.10.1; extra == 'all'
Requires-Dist: pre-commit<3.0.0,>=2.16.0; extra == 'all'
Requires-Dist: pylint<3.0.0,>=2.12.2; extra == 'all'
Requires-Dist: pytest<6.0.0,>=5.2; extra == 'all'
